[
  {
    "title": "Search News Buzz Video Recap: Google Rank Volatility Heated, AI Overviews To Send Less Traffic, Opt Out Of It, Yahoo Scouts & Bing AI Performance Report",
    "link": "https://www.seroundtable.com/video-01-30-2026-40847.html",
    "description": "This week, we covered more ongoing Google search ranking volatility - January was a heated month. Google AI Overviews show more button officially flows to AI Mode...",
    "source_id": "seroundtable",
    "pubDate": "2026-01-30 13:01:00"
  },
  {
    "title": "BofA\u2019s Top Stocks to Watch Ahead of Q4 Earnings and 2026 AI Pivot",
    "link": "https://za.investing.com/news/stock-market-news/bofas-top-stocks-to-watch-ahead-of-q4-earnings-and-2026-ai-pivot-93CH-4087639",
    "description": null,
    "source_id": "investing_za",
    "pubDate": "2026-01-30 13:00:09"
  },
  {
    "title": "BofA\u2019s Top Stocks to Watch Ahead of Q4 Earnings and 2026 AI Pivot",
    "link": "https://ca.investing.com/news/stock-market-news/bofas-top-stocks-to-watch-ahead-of-q4-earnings-and-2026-ai-pivot-93CH-4428968",
    "description": null,
    "source_id": "investing_ca",
    "pubDate": "2026-01-30 13:00:09"
  },
  {
    "title": "BofA\u2019s Top Stocks to Watch Ahead of Q4 Earnings and 2026 AI Pivot",
    "link": "https://ph.investing.com/news/stock-market-news/bofas-top-stocks-to-watch-ahead-of-q4-earnings-and-2026-ai-pivot-93CH-2207397",
    "description": null,
    "source_id": "investing_ph",
    "pubDate": "2026-01-30 13:00:09"
  },
  {
    "title": "BofA\u2019s Top Stocks to Watch Ahead of Q4 Earnings and 2026 AI Pivot",
    "link": "https://au.investing.com/news/stock-market-news/bofas-top-stocks-to-watch-ahead-of-q4-earnings-and-2026-ai-pivot-93CH-4232257",
    "description": null,
    "source_id": "investing_au",
    "pubDate": "2026-01-30 13:00:09"
  }
]