[
  {
    "title": "The end of oil? As fuel shocks cascade, 53 nations gather to plan a fossil fuel phaseout",
    "link": "https://www.hindustantimes.com/world-news/us-news/the-end-of-oil-as-fuel-shocks-cascade-53-nations-gather-to-plan-a-fossil-fuel-phaseout-101776840642518.html",
    "description": "The end of oil? As fuel shocks cascade, 53 nations gather to plan a fossil fuel phaseout",
    "source_id": "hindustantimes",
    "pubDate": "2026-04-22 06:50:42"
  },
  {
    "title": "The end of oil? As fuel shocks cascade, 53 nations gather to plan a fossil fuel phaseout",
    "link": "https://www.newsdrum.in/international/the-end-of-oil-as-fuel-shocks-cascade-53-nations-gather-to-plan-a-fossil-fuel-phaseout-11753124",
    "description": "Sydney, Apr 22 (The Conversation) US President Donald Trump is a longtime climate denier and oil industry ally, who sums up his own energy policy as \u201cdrill, baby, drill\u201d. Yet he is doing more than almost anyone to speed up the global shift from fossil fuels to clean energy and electric vehicles (EVs). After the US and Israel struck Iran in late February, Tehran closed the Strait of Hormuz and triggered the largest disruption of oil supply in history. Ironically for Trump and his oil industry donors, this crisis may be an irreversible tipping point for clean energy. For years, fossil fuel advocates spruiked oil, gas and coal as \u201creliable\u201d energy. That narrative has been reversed. Fossil fuels have become expensive and unreliable, while renewables are cheap, reliable and secure. For the first time ever, more than 50 nations will gather next week in Colombia to hash out how to wind down and end their dependence on coal, oil and gas. The history-making conference was planned before the Iran war. But this year\u2019s energy crisis has greatly raised the stakes. The oil crisis is real Iran\u2019s closure of the narrow Strait of Hormuz stopped oil tankers reaching their destinations. But that wasn\u2019t all. More than 60 gas and oil sites have been damaged in the conflict so far. Even if a durable ceasefire is reached, these impacts will reverberate for months and years to come. Around 80% of the trapped crude oil was destined for the Asia-Pacific. Faced with dwindling supply, the region\u2019s governments are implementing emergency measures such as sending workers home, banning government travel, rationing fuel and cutting school hours. The problem is especially bad in the Pacific. Many island nations use diesel for power generation. In response, leaders declared a regional emergency. Fuel import bills were already a major burden for Pacific nations, leading to efforts to switch to local renewables. Fuel bills could rise by A$933 million in Fiji (nearly three times the healthcare budget). Scrambling for energy When energy supplies are disrupted, leaders have three options: find alternate supplies, reduce use or switch to alternatives. In the very short term, countries aim to shore up supply, just as Australian Prime Minister Anthony Albanese did last week in Malaysia. Countries have also moved to reduce use. This can have lasting effects. During the Middle East oil shocks of the 1970s, oil prices tripled and then doubled again. Authorities responded by improving energy productivity to do more with less. The world\u2019s final oil demand per capita peaked in 1979 and has never recovered. But the real difference from half a century ago is that fossil fuel alternatives are ready for prime time. Since the 1970s, the price of solar panels has fallen 99.9%, while the cost of wind has fallen 91% since 1984. Battery prices have fallen 99% since 1991. This means it\u2019s now viable for many nations to switch to these alternatives. The European Union will accelerate electrification, after its fossil fuel bill increased more than $36 billion since February. France has doubled state aid to help households switch to EVs and electrify home heating. Import-dependent South Korea gets 70% of its crude oil through the Strait of Hormuz. It now plans to double renewables capacity within four years. Electric vehicles at the tipping point? This year\u2019s oil shock shows signs of creating an unplanned social tipping point \u2013 a threshold for self-propelling change beyond which systems shift from one state to another. Climate scientists warn of climate tipping points which amplify feedback and accelerate warming. But social scientists also point to positive tipping points \u2013 collective action that rapidly accelerates climate action. The rush to EVs is a case in point. In Australia, petrol prices surged almost 50% in March, and diesel more than 70%. It\u2019s no surprise new EV sales are at an all-time high, while secondhand EV sales more than doubled last month. Australia\u2019s 1.3 million hybrid and battery electric vehicles avoid almost 15 million litres of petrol and diesel use every week. The rush to electric transport is global. Most new Chinese cars are powered by batteries, not oil. Battery electric vehicles outsold petrol cars for the first time in Europe in January. A conference to quit fossil fuels The routine burning of coal, oil and gas is the primary driver of the climate crisis. The world\u2019s highest court last year made clear nations have obligations to stop burning fossil fuels. But fossil fuels have barely been mentioned in 30 years of global climate negotiations, due in part to blocking efforts by big fossil fuel exporters and lobbyists. Frustrated by slow progress, a coalition of nations has bypassed global climate talks to discuss how to actually phase out fossil fuels. The first of these summits will take place next week. More than 50 nations will gather in Santa Marta, Colombia, to discuss a potential standalone treaty to manage fossil-fuel phaseout while protecting workers and financial systems. Colombian Environment Minister Irene Ve\u0301lez Torres says it comes at the \u201cbest possible moment\u201d, as the oil crisis focuses global attention on fossil fuel dependency. If next week\u2019s summit produces real momentum to wean off fossil fuels amid the energy crisis, we might look back at it as a social tipping point where early adopters move in earnest \u2013 and make it easier for the rest of the world to follow. (The Conversation) SCY SCY",
    "source_id": "newsdrum_in",
    "pubDate": "2026-04-22 06:50:35"
  },
  {
    "title": "Fossil fuels do not guarantee energy security: COP31 presidency",
    "link": "https://www.eco-business.com/news/fossil-fuels-do-not-guarantee-energy-security-cop31-presidency/",
    "description": "As Earth Day 2026 rallies communities to speed the shift from fossil fuels, COP31 president Murat Kurum urges countries to close the gap between global climate needs and available resources during the Petersberg Climate Dialogue.",
    "source_id": "eco_business",
    "pubDate": "2026-04-22 06:40:00"
  },
  {
    "title": "The end of oil? 53 nations gather to plan a fossil fuel phaseout",
    "link": "https://nation.africa/kenya/news/world/the-end-of-oil-53-nations-gather-to-plan-a-fossil-fuel-phaseout-5431974",
    "description": "Nations will gather in Colombia to hash out how to end their dependence on coal, oil and gas.",
    "source_id": "nation",
    "pubDate": "2026-04-22 06:35:13"
  },
  {
    "title": "US family returns five ancient artefacts to Greece in voluntary repatriation",
    "link": "https://www.voria.gr/article/us-family-returns-five-ancient-artefacts-greece-voluntary-repatriation",
    "description": "Two 6th-century BC Attic vases are among five antiquities handed back after more than four decades abroad",
    "source_id": "voria_gr",
    "pubDate": "2026-04-22 06:23:16"
  }
]