[
  {
    "title": "Kacey Musgraves has hilarious response to \u2018UFO analyst\u2019 debunking her space sighting",
    "link": "https://www.independent.co.uk/arts-entertainment/music/news/kacey-musgraves-ufo-sighting-response-b2956099.html",
    "description": "\u2018Space Cowboy\u2019 singer said she saw suspicious orbs on her flight from Texas to Nashville",
    "source_id": "independentuk",
    "pubDate": "2026-04-12 14:37:47"
  },
  {
    "title": "Nearly a century of wondering: The American UFO saga, in reality and in fiction",
    "link": "https://www.reporterherald.com/2026/04/12/what-on-earth-chronology/",
    "description": "Sightings and investigations date back to the first widely reported one in 1947.",
    "source_id": "reporterherald",
    "pubDate": "2026-04-12 14:20:39"
  },
  {
    "title": "Nearly a century of wondering: The American UFO saga, in reality and in fiction",
    "link": "https://www.canoncitydailyrecord.com/2026/04/12/what-on-earth-chronology/",
    "description": "Sightings and investigations date back to the first widely reported one in 1947.",
    "source_id": "canoncitydailyrecord",
    "pubDate": "2026-04-12 14:20:39"
  },
  {
    "title": "Nearly a century of wondering: The American UFO saga, in reality and in fiction",
    "link": "https://www.timescall.com/2026/04/12/what-on-earth-chronology/",
    "description": "Sightings and investigations date back to the first widely reported one in 1947.",
    "source_id": "timescall",
    "pubDate": "2026-04-12 14:20:39"
  },
  {
    "title": "Nearly a century of wondering: The American UFO saga, in reality and in fiction",
    "link": "https://www.fortmorgantimes.com/2026/04/12/what-on-earth-chronology/",
    "description": "Sightings and investigations date back to the first widely reported one in 1947.",
    "source_id": "fortmorgantimes",
    "pubDate": "2026-04-12 14:20:39"
  }
]